Metadata-Version: 2.1
Name: fastapi-base-tools
Version: 0.0.5
Summary: some fastapi base tools
Home-page: https://github.com/yprocfly/fastapi-base-tools
Author: Yang Peng
Author-email: yp_rocfly@foxmail.com
License: UNKNOWN
Keywords: fastapi,base,tools
Platform: UNKNOWN
Classifier: Programming Language :: Python :: 3
Classifier: Programming Language :: Python :: 3.7
Classifier: License :: OSI Approved :: MIT License
Classifier: Operating System :: OS Independent
